rolling_ta/__init__.py
rolling_ta/env.py
rolling_ta/indicator.py
rolling_ta/logging.py
rolling_ta/numba_indicator.py
rolling_ta/data/__init__.py
rolling_ta/data/csv_loader.py
rolling_ta/data/data_loader.py
rolling_ta/data/data_writer.py
rolling_ta/data/xlsx_loader.py
rolling_ta/data/xlsx_writer.py
rolling_ta/extras/__init__.py
rolling_ta/extras/numba.py
rolling_ta/momentum/__init__.py
rolling_ta/momentum/bop.py
rolling_ta/momentum/rsi.py
rolling_ta/momentum/stochastic_rsi.py
rolling_ta/omni/__init__.py
rolling_ta/omni/ichimoku_cloud.py
rolling_ta/trend/__init__.py
rolling_ta/trend/adx.py
rolling_ta/trend/dmi.py
rolling_ta/trend/donchian_channels.py
rolling_ta/trend/ema.py
rolling_ta/trend/hma.py
rolling_ta/trend/lr.py
rolling_ta/trend/lrf.py
rolling_ta/trend/lrr.py
rolling_ta/trend/macd.py
rolling_ta/trend/sma.py
rolling_ta/trend/wma.py
rolling_ta/volatility/__init__.py
rolling_ta/volatility/atr.py
rolling_ta/volatility/bb.py
rolling_ta/volatility/tr.py
rolling_ta/volume/__init__.py
rolling_ta/volume/mfi.py
rolling_ta/volume/obv.py
rolling_ta/volume/vwap.py
rolling_ta-0.8.3.dist-info/METADATA
rolling_ta-0.8.3.dist-info/WHEEL
rolling_ta-0.8.3.dist-info/licenses/LICENSE
rolling_ta-0.8.3.dist-info/RECORD
