Metadata-Version: 2.3
Name: rolling_ta
Version: 0.8.3
Summary: Simple, single responsibility API for fast technical indicator calculations and incrementation.
Project-URL: Homepage, https://github.com/Kwuasimoto/rolling-ta
Author-email: Kwuasimoto <thomasdouglasshank@gmail.com>
License-File: LICENSE
Classifier: Operating System :: OS Independent
Classifier: Programming Language :: Python :: 3
Requires-Python: >=3.8
Requires-Dist: numba==0.60.0
Requires-Dist: pandas==2.2.2
Requires-Dist: python-dotenv==1.0.1
Provides-Extra: dev
Requires-Dist: black; extra == 'dev'
